hface/__init__.py
hface/__main__.py
hface/_configuration.py
hface/_error_codes.py
hface/_typing.py
hface/py.typed
hface/cli/__init__.py
hface/cli/_main.py
hface/cli/_commands/__init__.py
hface/cli/_commands/base.py
hface/cli/_commands/client.py
hface/cli/_commands/proxy.py
hface/cli/_commands/server.py
hface/cli/_options/__init__.py
hface/cli/_options/client.py
hface/cli/_options/common.py
hface/cli/_options/server.py
hface/client/__init__.py
hface/client/_base.py
hface/client/_client.py
hface/client/_controllers.py
hface/client/_exceptions.py
hface/client/_models.py
hface/client/_proxy_client.py
hface/connections/__init__.py
hface/connections/_connections.py
hface/connections/_listeners.py
hface/connections/_openers.py
hface/connections/_transports.py
hface/events/__init__.py
hface/events/_events.py
hface/networking/__init__.py
hface/networking/_networking.py
hface/networking/_quic.py
hface/networking/_typing.py
hface/protocols/__init__.py
hface/protocols/_factories.py
hface/protocols/_protocols.py
hface/protocols/_registry.py
hface/protocols/http1/__init__.py
hface/protocols/http1/_factories.py
hface/protocols/http1/_helpers.py
hface/protocols/http1/_protocol.py
hface/protocols/http2/__init__.py
hface/protocols/http2/_factories.py
hface/protocols/http2/_protocol.py
hface/protocols/http3/__init__.py
hface/protocols/http3/_factories.py
hface/protocols/http3/_protocol.py
hface/protocols/http3/_quic.py
hface/server/__init__.py
hface/server/_asgi.py
hface/server/_base.py
hface/server/_exceptions.py
hface/server/_models.py
hface/server/_proxy_server.py
hface/server/_server.py
hface/server/examples/__init__.py
hface/server/examples/alt_svc.py
hface/server/examples/asgi_echo.py
hface/server/examples/hello.py
hface-0.1.dist-info/AUTHORS
hface-0.1.dist-info/LICENSE
hface-0.1.dist-info/METADATA
hface-0.1.dist-info/NOTICE
hface-0.1.dist-info/WHEEL
hface-0.1.dist-info/entry_points.txt
hface-0.1.dist-info/top_level.txt
hface-0.1.dist-info/RECORD
