Metadata-Version: 2.1
Name: hface
Version: 0.1
Summary: Hackable HTTP/{1,2,3} {client,server,proxy}
Home-page: https://github.com/akamai/hface
Author: Miloslav Pojman
Author-email: mpojman@akamai.com
License: Apache License 2.0
Project-URL: Documentation, https://hface.readthedocs.io/
Project-URL: Source Code, https://github.com/akamai/hface
Keywords: HTTP,HTTP/2,HTTP/3,server,client,proxy,AnyIO,asyncio,Trio
Classifier: Development Status :: 3 - Alpha
Classifier: Environment :: Console
Classifier: Environment :: Web Environment
Classifier: Framework :: AnyIO
Classifier: Framework :: AsyncIO
Classifier: Framework :: Trio
Classifier: Intended Audience :: Developers
Classifier: License :: OSI Approved :: Apache Software License
Classifier: Operating System :: OS Independent
Classifier: Programming Language :: Python
Classifier: Programming Language :: Python :: 3
Classifier: Programming Language :: Python :: 3 :: Only
Classifier: Programming Language :: Python :: 3.7
Classifier: Programming Language :: Python :: 3.8
Classifier: Programming Language :: Python :: 3.9
Classifier: Programming Language :: Python :: 3.10
Classifier: Programming Language :: Python :: Implementation :: CPython
Classifier: Programming Language :: Python :: Implementation :: PyPy
Classifier: Topic :: Internet
Classifier: Topic :: Internet :: WWW/HTTP
Classifier: Topic :: Internet :: WWW/HTTP :: HTTP Servers
Classifier: Topic :: Software Development :: Libraries
Classifier: Topic :: Software Development :: Libraries :: Python Modules
Classifier: Topic :: System :: Networking
Classifier: Typing :: Typed
Requires-Python: >=3.7
License-File: LICENSE
License-File: NOTICE
License-File: AUTHORS
Requires-Dist: aioquic
Requires-Dist: anyio
Requires-Dist: h11
Requires-Dist: h2
Requires-Dist: importlib-metadata
Provides-Extra: all
Requires-Dist: anyio[trio] ; extra == 'all'
Requires-Dist: uvloop ; extra == 'all'
Provides-Extra: dev
Requires-Dist: black ; extra == 'dev'
Requires-Dist: flake8 ; extra == 'dev'
Requires-Dist: isort ; extra == 'dev'
Requires-Dist: pytest ; extra == 'dev'
Requires-Dist: mypy (>=0.981) ; extra == 'dev'
Provides-Extra: trio
Requires-Dist: anyio[trio] ; extra == 'trio'
Provides-Extra: uvloop
Requires-Dist: uvloop ; extra == 'uvloop'
